ripple/Performance_test.py
ripple/VERSION
ripple/__init__.py
ripple/correlation.py
ripple/dynamic.py
ripple/static.py
ripple_hpc-1.0.0.dist-info/licenses/LICENSE
ripple_hpc-1.0.0.dist-info/METADATA
ripple_hpc-1.0.0.dist-info/WHEEL
ripple_hpc-1.0.0.dist-info/top_level.txt
ripple_hpc-1.0.0.dist-info/RECORD
