Metadata-Version: 2.4
Name: Ripple-hpc
Version: 1.0.0
Summary: Ripple is a Python package designed to analyze particle-motion correlation functions at scale on HPC.
Home-page: https://github.com/orgs/Frost-group/repositories/Ripple
Author: LuciusLiu
Author-email: Lucius Liu <l.liu21@imperial.ac.uk>
License: MIT License
Project-URL: homepage, https://github.com/Frost-group/Ripple
Project-URL: repository, https://github.com/Frost-group/Ripple
Classifier: Programming Language :: Python :: 3
Classifier: License :: OSI Approved :: MIT License
Classifier: Operating System :: OS Independent
Requires-Python: >=3.9
License-File: LICENSE
Requires-Dist: numpy
Requires-Dist: ase
Requires-Dist: h5py
Requires-Dist: joblib
Requires-Dist: psutil
Dynamic: author
Dynamic: home-page
Dynamic: license-file
Dynamic: requires-python
